fastaws/__init__.py
fastaws/auth.py
fastaws/core.py
fastaws/enums.py
fastaws/exceptions.py
fastaws/s3/client.py
fastaws/s3/models.py
fastaws/ses/client.py
fastaws/sqs/client.py
fastaws/sqs/models.py
fastaws/sqs/utils.py
fastaws-0.0.14.dist-info/METADATA
fastaws-0.0.14.dist-info/WHEEL
fastaws-0.0.14.dist-info/licenses/LICENSE
fastaws-0.0.14.dist-info/RECORD
