Metadata-Version: 2.1
Name: fastaws
Version: 0.0.14
Summary: A fast, simple, async Python library for some AWS services (S3, SES, SQS)
Project-URL: Homepage, https://github.com/waydegg/fastaws
Project-URL: Source, https://github.com/waydegg/fastaws
Author-email: Wayde Gilliam <waydegilliam@gmail.com>
License: MIT
License-File: LICENSE
Keywords: asyncio,aws,python
Classifier: Development Status :: 3 - Alpha
Classifier: Environment :: Console
Classifier: Framework :: AsyncIO
Classifier: Intended Audience :: Developers
Classifier: License :: OSI Approved :: MIT License
Classifier: Operating System :: MacOS
Classifier: Operating System :: POSIX :: Linux
Classifier: Programming Language :: Python :: 3 :: Only
Classifier: Programming Language :: Python :: 3.10
Classifier: Programming Language :: Python :: 3.11
Classifier: Topic :: Internet
Classifier: Topic :: Software Development :: Libraries :: Python Modules
Requires-Python: >=3.10.4
Requires-Dist: aiofiles
Requires-Dist: beautifulsoup4
Requires-Dist: httpx
Requires-Dist: lxml
Requires-Dist: structlog
Provides-Extra: dev
Requires-Dist: black; extra == 'dev'
Requires-Dist: isort; extra == 'dev'
